LICENSE.txt
MANIFEST.in
setup.cfg
setup.py
examples/abalone_ex.py
examples/mushroom_ex.py
pyrite/__init__.py
pyrite/pyrite.py
pyrite/pyrite_eval.py
pyrite/test/__init__.py
pyrite2.egg-info/PKG-INFO
pyrite2.egg-info/SOURCES.txt
pyrite2.egg-info/dependency_links.txt
pyrite2.egg-info/requires.txt
pyrite2.egg-info/top_level.txt