Metadata-Version: 1.0
Name: pyrite2
Version: 0.1.2
Summary: Anomaly Detection in High Dimensional Heterogeneous Datasets
Home-page: http://pyrite.startup.ml
Author: StartupML
Author-email: team@startup.ml
License: LICENSE.txt
Platform: UNKNOWN
